{
  "resourceType": "Patient",
  "id": "opioid-review-useful",
  "meta": {
    "profile": [
      "http://hl7.org/fhir/us/cdc-opioid-cpg/StructureDefinition/OpioidReviewUsefulPatient"
    ],
    "extension": [
      {
        "url": "http://hl7.org/fhir/StructureDefinition/instance-name",
        "valueString": "Opioid Review Useful Patient Example"
      },
      {
        "url": "http://hl7.org/fhir/StructureDefinition/instance-description",
        "valueMarkdown": "This is an opioid review useful patient example for the *Opioid Review Useful Patient Profile*."
      }
    ]
  },
  "identifier": [
    {
      "use": "usual",
      "system": "urn:ietf:rfc:3986",
      "value": "http://example.com/Patient/12345"
    }
  ],
  "name": [
    {
      "family": "Appleseed",
      "given": [
        "Johnny"
      ]
    }
  ],
  "gender": "male",
  "birthDate": "1983-01-10",
  "address": [
    {
      "use": "home",
      "type": "postal",
      "line": [
        "751 E Apple Drive"
      ],
      "city": "Novi",
      "district": "Oakland County",
      "state": "MI",
      "postalCode": "48376"
    }
  ]
}